{
  "name": "Ability",
  "expr": "Ability",
  "variations": [
    {
      "template": "It can't attack its controller.",
      "rts": [
        "It can't attack its controller."
      ]
    },
    {
      "template": "Mana abilities can't be copied.",
      "rts": [
        "Mana abilities can't be copied."
      ]
    },
    {
      "template": "Mana abilities can't be targeted.",
      "rts": [
        "Mana abilities can't be targeted."
      ]
    },
    {
      "template": "Select from among all legal targets.",
      "rts": [
        "Select from among all legal targets."
      ]
    },
    {
      "template": "{R/W} can be paid with either {R} or {W}.",
      "rts": [
        "{R/W} can be paid with either {R} or {W}."
      ]
    },
    {
      "template": "It won't be affected by the spell or ability.",
      "rts": [
        "It won't be affected by the spell or ability."
      ]
    },
    {
      "template": "A triggered ability uses the words \"when,\" \"whenever,\" or \"at.\"",
      "rts": [
        "A triggered ability uses the words \"when,\" \"whenever,\" or \"at.\""
      ]
    },
    {
      "template": "It can be in any deck whose commander's color identity includes green.",
      "rts": [
        "It can be in any deck whose commander's color identity includes green."
      ]
    },
    {
      "template": "Sacrificing an artifact for mana to activate an ability doesn't count.",
      "rts": [
        "Sacrificing an artifact for mana to activate an ability doesn't count."
      ]
    },
    {
      "template": "You see all cards that player could see and make all decisions for them.",
      "rts": [
        "You see all cards that player could see and make all decisions for them."
      ]
    },
    {
      "template": "The token is an artifact with \"{T}: Add {C}. This mana can't be spent to cast a nonartifact spell.\"",
      "rts": [
        "The token is an artifact with \"{T}: Add {C}. This mana can't be spent to cast a nonartifact spell.\""
      ]
    }
  ]
}